crawler/__init__.py
crawler/crawler.py
Crawlersteamcommunity-0.1.dist-info/METADATA
Crawlersteamcommunity-0.1.dist-info/WHEEL
Crawlersteamcommunity-0.1.dist-info/top_level.txt
Crawlersteamcommunity-0.1.dist-info/RECORD
